local_data/__init__.py
local_data/get_test_data.py
local_data/setup_text.py
local_data/test.py
local_data/test_tariffs.py
ts_tariffs/__init__.py
ts_tariffs/billing.py
ts_tariffs/meters.py
ts_tariffs/tariffs.py
ts_tariffs/ts_utils.py
ts_tariffs/units.py
ts_tariffs/utils.py
ts_tariffs/examples/__init__.py
ts_tariffs/examples/data_getters.py
ts_tariffs/examples/data_urls.py
ts_tariffs-3.2.4.dist-info/LICENSE
ts_tariffs-3.2.4.dist-info/METADATA
ts_tariffs-3.2.4.dist-info/WHEEL
ts_tariffs-3.2.4.dist-info/top_level.txt
ts_tariffs-3.2.4.dist-info/RECORD
